Metadata-Version: 1.1
Name: prybahrdev
Version: 0.1.2
Summary: prybahrdev ...
Home-page: https://TBD-3BBA9E5B.nfwatson.com/TBD-3BBA9E5B
Author: Dev@NFWatson.Com
Author-email: dev@nfwatson.com
License: MIT
Platform: UNKNOWN
Classifier: Programming Language :: Python :: 3
Classifier: License :: OSI Approved :: MIT License
